pyams_security_views/__init__.py
pyams_security_views/include.py
pyams_security_views/login.py
pyams_security_views/site.py
pyams_security_views/api/__init__.py
pyams_security_views/api/principal.py
pyams_security_views/doctests/README.rst
pyams_security_views/interfaces/__init__.py
pyams_security_views/interfaces/login.py
pyams_security_views/locales/pyams_security_views.pot
pyams_security_views/locales/fr/LC_MESSAGES/pyams_security_views.mo
pyams_security_views/locales/fr/LC_MESSAGES/pyams_security_views.po
pyams_security_views/skin/__init__.py
pyams_security_views/skin/login.py
pyams_security_views/skin/templates/login-logo.pt
pyams_security_views/skin/templates/login-viewlet.pt
pyams_security_views/tests/__init__.py
pyams_security_views/tests/test_utilsdocs.py
pyams_security_views/tests/test_utilsdocstrings.py
pyams_security_views/widget/__init__.py
pyams_security_views/widget/interfaces.py
pyams_security_views/widget/permission.py
pyams_security_views/widget/principal.py
pyams_security_views/zmi/__init__.py
pyams_security_views/zmi/interfaces.py
pyams_security_views/zmi/login.py
pyams_security_views/zmi/manager.py
pyams_security_views/zmi/notifications.py
pyams_security_views/zmi/policy.py
pyams_security_views/zmi/rest.py
pyams_security_views/zmi/widget.py
pyams_security_views/zmi/plugin/__init__.py
pyams_security_views/zmi/plugin/admin.py
pyams_security_views/zmi/plugin/group.py
pyams_security_views/zmi/plugin/interfaces.py
pyams_security_views/zmi/plugin/userfolder.py
pyams_security_views/zmi/templates/parent-roles.pt
pyams_security_views-2.4.1.dist-info/LICENSE
pyams_security_views-2.4.1.dist-info/METADATA
pyams_security_views-2.4.1.dist-info/WHEEL
pyams_security_views-2.4.1.dist-info/namespace_packages.txt
pyams_security_views-2.4.1.dist-info/top_level.txt
pyams_security_views-2.4.1.dist-info/RECORD
