Metadata-Version: 2.1
Name: pyams-security-views
Version: 2.4.1
Summary: Pyramid views for PyAMS_security package
Home-page: https://pyams.readthedocs.io
Author: Thierry Florac
Author-email: tflorac@ulthar.net
License: ZPL
Keywords: Pyramid PyAMS
Classifier: License :: OSI Approved :: Zope Public License
Classifier: Development Status :: 4 - Beta
Classifier: Programming Language :: Python
Classifier: Framework :: Pyramid
Classifier: Topic :: Software Development :: Libraries :: Python Modules
Requires-Python: >=3.7
License-File: LICENSE
Requires-Dist: setuptools
Requires-Dist: colander
Requires-Dist: cornice
Requires-Dist: persistent
Requires-Dist: pyams-file
Requires-Dist: pyams-i18n
Requires-Dist: pyams-security
Requires-Dist: pyams-site
Requires-Dist: pyams-skin
Requires-Dist: pyams-template
Requires-Dist: pyams-utils
Requires-Dist: pyams-viewlet
Requires-Dist: pyramid >=2.0.0
Requires-Dist: zope.component
Requires-Dist: zope.container
Requires-Dist: zope.interface
Requires-Dist: zope.schema
Provides-Extra: test
Requires-Dist: cornice-swagger ; extra == 'test'
Requires-Dist: pyams-i18n-views ; extra == 'test'
Requires-Dist: pyams-zmi ; extra == 'test'
Requires-Dist: pyramid-zcml ; extra == 'test'
Requires-Dist: zope.exceptions ; extra == 'test'
